asterisk/__init__.py
asterisk/agi.py
asterisk/agitb.py
asterisk/config.py
asterisk/fastagi.py
asterisk/manager.py
pyst2-0.5.1.dist-info/METADATA
pyst2-0.5.1.dist-info/WHEEL
pyst2-0.5.1.dist-info/top_level.txt
pyst2-0.5.1.dist-info/RECORD
