Metadata-Version: 1.1
Name: pyst2
Version: 0.5.1
Summary: A Python Interface to Asterisk
Home-page: https://github.com/rdegges/pyst2
Author: Randall Degges
Author-email: r@rdegges.com
License: Python Software Foundation License / GNU Library or Lesser General Public License (LGPL) / UNLICENSE
Keywords: python asterisk agi ami telephony telephony sip voip
Platform: Any
Classifier: Development Status :: 5 - Production/Stable
Classifier: Environment :: Other Environment
Classifier: Intended Audience :: Developers
Classifier: Intended Audience :: Telecommunications Industry
Classifier: Operating System :: OS Independent
Classifier: Programming Language :: Python
Classifier: Programming Language :: Python :: 2.6
Classifier: Programming Language :: Python :: 2.7
Classifier: Programming Language :: Python :: 3
Classifier: Programming Language :: Python :: 3.2
Classifier: Programming Language :: Python :: 3.3
Classifier: Programming Language :: Python :: 3.4
Classifier: Topic :: Communications :: Internet Phone
Classifier: Topic :: Communications :: Telephony
Classifier: Topic :: Software Development :: Libraries :: Python Modules
